{
  "fetched_at": "2026-06-30T13:22:24.554552Z",
  "report_date": "2026-06-29",
  "yesterday": [
    {
      "sessionSource": "(direct)",
      "sessionMedium": "(none)",
      "sessions": "34",
      "activeUsers": "27",
      "conversions": "0",
      "purchaseRevenue": "0",
      "ecommercePurchases": "0"
    },
    {
      "sessionSource": "youtube.com",
      "sessionMedium": "referral",
      "sessions": "12",
      "activeUsers": "9",
      "conversions": "0",
      "purchaseRevenue": "0",
      "ecommercePurchases": "0"
    },
    {
      "sessionSource": "google",
      "sessionMedium": "organic",
      "sessions": "9",
      "activeUsers": "5",
      "conversions": "0",
      "purchaseRevenue": "0",
      "ecommercePurchases": "0"
    },
    {
      "sessionSource": "(data not available)",
      "sessionMedium": "(data not available)",
      "sessions": "5",
      "activeUsers": "4",
      "conversions": "0",
      "purchaseRevenue": "0",
      "ecommercePurchases": "0"
    },
    {
      "sessionSource": "m.youtube.com",
      "sessionMedium": "referral",
      "sessions": "3",
      "activeUsers": "3",
      "conversions": "0",
      "purchaseRevenue": "0",
      "ecommercePurchases": "0"
    },
    {
      "sessionSource": "shopify.com",
      "sessionMedium": "referral",
      "sessions": "3",
      "activeUsers": "1",
      "conversions": "1",
      "purchaseRevenue": "129.6",
      "ecommercePurchases": "1"
    },
    {
      "sessionSource": "",
      "sessionMedium": "",
      "sessions": "2",
      "activeUsers": "1",
      "conversions": "0",
      "purchaseRevenue": "0",
      "ecommercePurchases": "0"
    },
    {
      "sessionSource": "ig",
      "sessionMedium": "social",
      "sessions": "2",
      "activeUsers": "1",
      "conversions": "0",
      "purchaseRevenue": "0",
      "ecommercePurchases": "0"
    },
    {
      "sessionSource": "judge.me",
      "sessionMedium": "referral",
      "sessions": "1",
      "activeUsers": "1",
      "conversions": "0",
      "purchaseRevenue": "0",
      "ecommercePurchases": "0"
    },
    {
      "sessionSource": "l.instagram.com",
      "sessionMedium": "referral",
      "sessions": "1",
      "activeUsers": "1",
      "conversions": "0",
      "purchaseRevenue": "0",
      "ecommercePurchases": "0"
    },
    {
      "sessionSource": "linktr.ee",
      "sessionMedium": "referral",
      "sessions": "1",
      "activeUsers": "1",
      "conversions": "1",
      "purchaseRevenue": "16.95",
      "ecommercePurchases": "1"
    }
  ],
  "prior_7_days": [
    {
      "sessionSource": "(direct)",
      "sessionMedium": "(none)",
      "sessions": "287",
      "activeUsers": "242",
      "conversions": "4",
      "purchaseRevenue": "294.95",
      "ecommercePurchases": "4"
    },
    {
      "sessionSource": "youtube.com",
      "sessionMedium": "referral",
      "sessions": "214",
      "activeUsers": "185",
      "conversions": "0",
      "purchaseRevenue": "0",
      "ecommercePurchases": "0"
    },
    {
      "sessionSource": "google",
      "sessionMedium": "organic",
      "sessions": "117",
      "activeUsers": "76",
      "conversions": "6",
      "purchaseRevenue": "423.678543",
      "ecommercePurchases": "6"
    },
    {
      "sessionSource": "l.instagram.com",
      "sessionMedium": "referral",
      "sessions": "22",
      "activeUsers": "2",
      "conversions": "0",
      "purchaseRevenue": "0",
      "ecommercePurchases": "0"
    },
    {
      "sessionSource": "m.youtube.com",
      "sessionMedium": "referral",
      "sessions": "22",
      "activeUsers": "20",
      "conversions": "0",
      "purchaseRevenue": "0",
      "ecommercePurchases": "0"
    },
    {
      "sessionSource": "(not set)",
      "sessionMedium": "(not set)",
      "sessions": "18",
      "activeUsers": "12",
      "conversions": "1",
      "purchaseRevenue": "60.700392",
      "ecommercePurchases": "1"
    },
    {
      "sessionSource": "ig",
      "sessionMedium": "social",
      "sessions": "13",
      "activeUsers": "9",
      "conversions": "1",
      "purchaseRevenue": "100",
      "ecommercePurchases": "1"
    },
    {
      "sessionSource": "linktr.ee",
      "sessionMedium": "referral",
      "sessions": "13",
      "activeUsers": "12",
      "conversions": "1",
      "purchaseRevenue": "16.95",
      "ecommercePurchases": "1"
    },
    {
      "sessionSource": "shopify.com",
      "sessionMedium": "referral",
      "sessions": "8",
      "activeUsers": "4",
      "conversions": "2",
      "purchaseRevenue": "171.6",
      "ecommercePurchases": "2"
    },
    {
      "sessionSource": "(data not available)",
      "sessionMedium": "(data not available)",
      "sessions": "5",
      "activeUsers": "4",
      "conversions": "0",
      "purchaseRevenue": "0",
      "ecommercePurchases": "0"
    },
    {
      "sessionSource": "statics.teams.cdn.office.net",
      "sessionMedium": "referral",
      "sessions": "3",
      "activeUsers": "2",
      "conversions": "0",
      "purchaseRevenue": "0",
      "ecommercePurchases": "0"
    },
    {
      "sessionSource": "tiktok.com",
      "sessionMedium": "referral",
      "sessions": "3",
      "activeUsers": "3",
      "conversions": "0",
      "purchaseRevenue": "0",
      "ecommercePurchases": "0"
    },
    {
      "sessionSource": "",
      "sessionMedium": "",
      "sessions": "2",
      "activeUsers": "1",
      "conversions": "0",
      "purchaseRevenue": "0",
      "ecommercePurchases": "0"
    },
    {
      "sessionSource": "admin.shopify.com",
      "sessionMedium": "referral",
      "sessions": "2",
      "activeUsers": "1",
      "conversions": "0",
      "purchaseRevenue": "0",
      "ecommercePurchases": "0"
    },
    {
      "sessionSource": "duckduckgo",
      "sessionMedium": "organic",
      "sessions": "2",
      "activeUsers": "2",
      "conversions": "0",
      "purchaseRevenue": "0",
      "ecommercePurchases": "0"
    },
    {
      "sessionSource": "goaffpro.com",
      "sessionMedium": "referral",
      "sessions": "2",
      "activeUsers": "2",
      "conversions": "0",
      "purchaseRevenue": "0",
      "ecommercePurchases": "0"
    },
    {
      "sessionSource": "google",
      "sessionMedium": "product_sync",
      "sessions": "2",
      "activeUsers": "2",
      "conversions": "0",
      "purchaseRevenue": "0",
      "ecommercePurchases": "0"
    },
    {
      "sessionSource": "judge.me",
      "sessionMedium": "referral",
      "sessions": "2",
      "activeUsers": "1",
      "conversions": "0",
      "purchaseRevenue": "0",
      "ecommercePurchases": "0"
    },
    {
      "sessionSource": "patreon.com",
      "sessionMedium": "referral",
      "sessions": "2",
      "activeUsers": "2",
      "conversions": "0",
      "purchaseRevenue": "0",
      "ecommercePurchases": "0"
    },
    {
      "sessionSource": "reddit.com",
      "sessionMedium": "referral",
      "sessions": "2",
      "activeUsers": "2",
      "conversions": "0",
      "purchaseRevenue": "0",
      "ecommercePurchases": "0"
    },
    {
      "sessionSource": "substack",
      "sessionMedium": "email",
      "sessions": "2",
      "activeUsers": "2",
      "conversions": "0",
      "purchaseRevenue": "0",
      "ecommercePurchases": "0"
    },
    {
      "sessionSource": "bing",
      "sessionMedium": "organic",
      "sessions": "1",
      "activeUsers": "0",
      "conversions": "0",
      "purchaseRevenue": "0",
      "ecommercePurchases": "0"
    },
    {
      "sessionSource": "ecosia.org",
      "sessionMedium": "organic",
      "sessions": "1",
      "activeUsers": "1",
      "conversions": "0",
      "purchaseRevenue": "0",
      "ecommercePurchases": "0"
    },
    {
      "sessionSource": "fidget-newton.tenereteam.com",
      "sessionMedium": "referral",
      "sessions": "1",
      "activeUsers": "1",
      "conversions": "0",
      "purchaseRevenue": "0",
      "ecommercePurchases": "0"
    },
    {
      "sessionSource": "mail.google.com",
      "sessionMedium": "referral",
      "sessions": "1",
      "activeUsers": "1",
      "conversions": "0",
      "purchaseRevenue": "0",
      "ecommercePurchases": "0"
    }
  ],
  "landing_pages": [
    {
      "landingPage": "/",
      "sessions": "29",
      "conversions": "1",
      "purchaseRevenue": "16.95"
    },
    {
      "landingPage": "/collections/frontpage",
      "sessions": "10",
      "conversions": "0",
      "purchaseRevenue": "0"
    },
    {
      "landingPage": "/products/fidget-macaron",
      "sessions": "8",
      "conversions": "1",
      "purchaseRevenue": "129.6"
    },
    {
      "landingPage": "",
      "sessions": "6",
      "conversions": "0",
      "purchaseRevenue": "0"
    },
    {
      "landingPage": "/collections/all",
      "sessions": "6",
      "conversions": "0",
      "purchaseRevenue": "0"
    },
    {
      "landingPage": "/products/fidget-newton",
      "sessions": "5",
      "conversions": "0",
      "purchaseRevenue": "0"
    },
    {
      "landingPage": "/products/cindells-handbag",
      "sessions": "3",
      "conversions": "0",
      "purchaseRevenue": "0"
    },
    {
      "landingPage": "/products/fidget-moons",
      "sessions": "3",
      "conversions": "0",
      "purchaseRevenue": "0"
    },
    {
      "landingPage": "/products/pride-moons",
      "sessions": "2",
      "conversions": "0",
      "purchaseRevenue": "0"
    },
    {
      "landingPage": "/products/fidget-hearts",
      "sessions": "1",
      "conversions": "0",
      "purchaseRevenue": "0"
    }
  ]
}